pulumi_utils/__init__.py
pulumi_utils-0.0.1.dist-info/LICENSE
pulumi_utils-0.0.1.dist-info/METADATA
pulumi_utils-0.0.1.dist-info/WHEEL
pulumi_utils-0.0.1.dist-info/top_level.txt
pulumi_utils-0.0.1.dist-info/RECORD
