Metadata-Version: 2.1
Name: pulumi-utils
Version: 0.0.1
Summary: Pulumi utilities
Home-page: https://github.com/pypa/pulumi-utils
Author: Jan Češpivo
Author-email: developers@allusio.com
License: UNKNOWN
Project-URL: Bug Tracker, https://github.com/allusio/pulumi-utils
Platform: UNKNOWN
Classifier: Programming Language :: Python :: 3
Classifier: License :: OSI Approved :: MIT License
Classifier: Operating System :: OS Independent
Requires-Python: >=3.6
License-File: LICENSE
